odoo/addons/ssi_py3o_sample/README.rst
odoo/addons/ssi_py3o_sample/__init__.py
odoo/addons/ssi_py3o_sample/__manifest__.py
odoo/addons/ssi_py3o_sample/reports/__init__.py
odoo/addons/ssi_py3o_sample/reports/report_parser.py
odoo/addons/ssi_py3o_sample/reports/report_sample.odt
odoo/addons/ssi_py3o_sample/reports/report_sample.xml
odoo/addons/ssi_py3o_sample/static/description/icon.png
odoo14_addon_ssi_py3o_sample-14.0.1.0.1.dev2.dist-info/METADATA
odoo14_addon_ssi_py3o_sample-14.0.1.0.1.dev2.dist-info/WHEEL
odoo14_addon_ssi_py3o_sample-14.0.1.0.1.dev2.dist-info/top_level.txt
odoo14_addon_ssi_py3o_sample-14.0.1.0.1.dev2.dist-info/RECORD
